{
  "Core": {
    "lineHeight-140%": {
      "value": "140%",
      "type": "lineHeights"
    },
    "lineHeight-150%": {
      "value": "150%",
      "type": "lineHeights"
    },
    "lineHeight-160%": {
      "value": "160%",
      "type": "lineHeights"
    },
    "Spacing": {
      "spacing-75(Base)": {
        "value": "4",
        "type": "spacing",
        "description": "Constant spacing-x-small"
      },
      "spacing-100": {
        "value": "{Spacing.spacing-75(Base)}*2",
        "type": "spacing",
        "description": "Constant spacing-small"
      },
      "spacing-300": {
        "value": "{Spacing.spacing-100}+ {Spacing.spacing-75(Base)}",
        "type": "spacing",
        "description": "Constant spacing-xm-small"
      },
      "spacing-400": {
        "value": "{Spacing.spacing-300}+ {Spacing.spacing-75(Base)}",
        "type": "spacing",
        "description": "Constant spacing-medium"
      },
      "spacing-500": {
        "value": "{Spacing.spacing-400} + {Spacing.spacing-75(Base)}",
        "type": "spacing",
        "description": "Constant spacing-x-medium"
      },
      "spacing-600": {
        "value": "{Spacing.spacing-500} + {Spacing.spacing-75(Base)}",
        "type": "spacing",
        "description": "Constant spacing-large"
      },
      "spacing-700": {
        "value": "{Spacing.spacing-600} + {Spacing.spacing-100}",
        "type": "spacing",
        "description": "Constant spacing-x-large"
      },
      "spacing-800": {
        "value": "{Spacing.spacing-700} + {Spacing.spacing-100}",
        "type": "spacing",
        "description": "Constant spacing-xx-large"
      },
      "spacing-900": {
        "value": "{Spacing.spacing-800} + {Spacing.spacing-100}",
        "type": "spacing",
        "description": "Constant spacing-xxx-large"
      },
      "spacing-1000": {
        "value": "{Spacing.spacing-900} + {Spacing.spacing-600}",
        "type": "spacing",
        "description": "Constant spacing-xxxx-large"
      },
      "spacing-50": {
        "value": "2",
        "type": "spacing",
        "description": "Constant spacing-xx-small"
      },
      "spacing-none": {
        "value": "0",
        "type": "spacing",
        "description": "Constant spacing-none"
      },
      "spacing-200": {
        "value": "10",
        "type": "spacing",
        "description": "Constant spacing-m-small"
      }
    },
    "Black": {
      "value": "#000000",
      "type": "color"
    },
    "White": {
      "value": "#ffffff",
      "type": "color"
    },
    "Scale": {
      "value": "1.125",
      "type": "sizing"
    },
    "text-50": {
      "value": "{text-75} /{Scale}",
      "type": "fontSizes"
    },
    "text-75": {
      "value": "{text-100} /{Scale}",
      "type": "fontSizes"
    },
    "text-100": {
      "value": "{text-200} /{Scale}",
      "type": "fontSizes"
    },
    "text-200": {
      "value": "{text-300(base)} /{Scale}",
      "type": "fontSizes"
    },
    "text-300(base)": {
      "value": "16",
      "type": "fontSizes"
    },
    "text-400": {
      "value": "{text-300(base)} *{Scale}",
      "type": "fontSizes"
    },
    "text-500": {
      "value": "{text-400} *{Scale}",
      "type": "fontSizes"
    },
    "text-600": {
      "value": "{text-500} * {Scale}",
      "type": "fontSizes"
    },
    "text-700": {
      "value": "{text-600} *{Scale}",
      "type": "fontSizes"
    },
    "text-800": {
      "value": "{text-700} *{Scale}",
      "type": "fontSizes"
    },
    "text-900": {
      "value": "{text-800} *{Scale}",
      "type": "fontSizes"
    },
    "text-1000": {
      "value": "{text-900} *{Scale}",
      "type": "fontSizes"
    },
    "text-1100": {
      "value": "{text-1000} *{Scale}",
      "type": "fontSizes"
    },
    "none": {
      "value": "None",
      "type": "lineHeights"
    },
    "Pretendard": {
      "value": "Pretendard",
      "type": "fontFamilies"
    },
    "regular": {
      "value": "Regular",
      "type": "fontWeights"
    },
    "medium": {
      "value": "Medium",
      "type": "fontWeights"
    },
    "semiBold": {
      "value": "SemiBold",
      "type": "fontWeights"
    },
    "bold": {
      "value": "Bold",
      "type": "fontWeights"
    },
    "Heading": {
      "XXL": {
        "value": {
          "fontFamily": "{Pretendard}",
          "fontWeight": "{bold}",
          "lineHeight": "{1Row.lineHeight-1100}",
          "fontSize": "{text-1100}",
          "letterSpacing": "{letterSpacing.0}",
          "paragraphSpacing": "{paragraphSpacing.0}",
          "paragraphIndent": "{paragraphIndent.0}",
          "textCase": "{textCase.none}",
          "textDecoration": "{textDecoration.none}"
        },
        "type": "typography"
      },
      "XL": {
        "value": {
          "fontFamily": "{Pretendard}",
          "fontWeight": "{bold}",
          "lineHeight": "{1Row.lineHeight-1000}",
          "fontSize": "{text-1000}",
          "letterSpacing": "{letterSpacing.0}",
          "paragraphSpacing": "{paragraphSpacing.0}",
          "paragraphIndent": "{paragraphIndent.0}",
          "textCase": "{textCase.none}",
          "textDecoration": "{textDecoration.none}"
        },
        "type": "typography"
      },
      "L": {
        "value": {
          "fontFamily": "{Pretendard}",
          "fontWeight": "{bold}",
          "lineHeight": "{1Row.lineHeight-800}",
          "fontSize": "{text-800}",
          "letterSpacing": "{letterSpacing.0}",
          "paragraphSpacing": "{paragraphSpacing.0}",
          "paragraphIndent": "{paragraphIndent.0}",
          "textCase": "{textCase.none}",
          "textDecoration": "{textDecoration.none}"
        },
        "type": "typography"
      },
      "M": {
        "value": {
          "fontFamily": "{Pretendard}",
          "fontWeight": "{bold}",
          "lineHeight": "{1Row.lineHeight-600}",
          "fontSize": "{text-600}",
          "letterSpacing": "{letterSpacing.0}",
          "paragraphSpacing": "{paragraphSpacing.0}",
          "paragraphIndent": "{paragraphIndent.0}",
          "textCase": "{textCase.none}",
          "textDecoration": "{textDecoration.none}"
        },
        "type": "typography"
      },
      "S": {
        "value": {
          "fontFamily": "{Pretendard}",
          "fontWeight": "{bold}",
          "lineHeight": "{1Row.lineHeight-500}",
          "fontSize": "{text-500}",
          "letterSpacing": "{letterSpacing.0}",
          "paragraphSpacing": "{paragraphSpacing.0}",
          "paragraphIndent": "{paragraphIndent.0}",
          "textCase": "{textCase.none}",
          "textDecoration": "{textDecoration.none}"
        },
        "type": "typography"
      },
      "XS": {
        "value": {
          "fontFamily": "{Pretendard}",
          "fontWeight": "{bold}",
          "lineHeight": "{1Row.lineHeight-300}",
          "fontSize": "{text-300(base)}",
          "letterSpacing": "{letterSpacing.0}",
          "paragraphSpacing": "{paragraphSpacing.0}",
          "paragraphIndent": "{paragraphIndent.0}",
          "textCase": "{textCase.none}",
          "textDecoration": "{textDecoration.none}"
        },
        "type": "typography"
      }
    },
    "1Row": {
      "lineHeight-1100": {
        "value": "48",
        "type": "lineHeights"
      },
      "lineHeight-1000": {
        "value": "44",
        "type": "lineHeights"
      },
      "lineHeight-900": {
        "value": "40",
        "type": "lineHeights"
      },
      "lineHeight-800": {
        "value": "36",
        "type": "lineHeights"
      },
      "lineHeight-700": {
        "value": "32",
        "type": "lineHeights"
      },
      "lineHeight-600": {
        "value": "28",
        "type": "lineHeights"
      },
      "lineHeight-500": {
        "value": "26",
        "type": "lineHeights"
      },
      "lineHeight-400": {
        "value": "24",
        "type": "lineHeights"
      },
      "lineHeight-300": {
        "value": "20",
        "type": "lineHeights"
      },
      "lineHeight-200": {
        "value": "18",
        "type": "lineHeights"
      },
      "lineHeight-100": {
        "value": "16",
        "type": "lineHeights"
      },
      "lineHeight-75": {
        "value": "14",
        "type": "lineHeights"
      },
      "lineHeight-50": {
        "value": "12",
        "type": "lineHeights"
      }
    },
    "Body": {
      "XXL": {
        "value": {
          "fontFamily": "{Pretendard}",
          "fontWeight": "{bold}",
          "lineHeight": "{1Row.lineHeight-600}",
          "fontSize": "{text-600}",
          "letterSpacing": "{letterSpacing.0}",
          "paragraphSpacing": "{paragraphSpacing.0}",
          "paragraphIndent": "{paragraphIndent.0}",
          "textCase": "{textCase.none}",
          "textDecoration": "{textDecoration.none}"
        },
        "type": "typography"
      },
      "XL": {
        "value": {
          "fontFamily": "{Pretendard}",
          "fontWeight": "{bold}",
          "lineHeight": "{1Row.lineHeight-500}",
          "fontSize": "{text-500}",
          "letterSpacing": "{letterSpacing.0}",
          "paragraphSpacing": "{paragraphSpacing.0}",
          "paragraphIndent": "{paragraphIndent.0}",
          "textCase": "{textCase.none}",
          "textDecoration": "{textDecoration.none}"
        },
        "type": "typography"
      },
      "L": {
        "value": {
          "fontFamily": "{Pretendard}",
          "fontWeight": "{semiBold}",
          "lineHeight": "{1Row.lineHeight-400}",
          "fontSize": "{text-400}",
          "letterSpacing": "{letterSpacing.0}",
          "paragraphSpacing": "{paragraphSpacing.0}",
          "paragraphIndent": "{paragraphIndent.0}",
          "textCase": "{textCase.none}",
          "textDecoration": "{textDecoration.none}"
        },
        "type": "typography"
      },
      "M": {
        "value": {
          "fontFamily": "{Pretendard}",
          "fontWeight": "{semiBold}",
          "lineHeight": "{1Row.lineHeight-300}",
          "fontSize": "{text-300(base)}",
          "letterSpacing": "{letterSpacing.0}",
          "paragraphSpacing": "{paragraphSpacing.0}",
          "paragraphIndent": "{paragraphIndent.0}",
          "textCase": "{textCase.none}",
          "textDecoration": "{textDecoration.none}"
        },
        "type": "typography"
      },
      "S": {
        "value": {
          "fontFamily": "{Pretendard}",
          "fontWeight": "{medium}",
          "lineHeight": "{1Row.lineHeight-200}",
          "fontSize": "{text-200}",
          "letterSpacing": "{letterSpacing.0}",
          "paragraphSpacing": "{paragraphSpacing.0}",
          "paragraphIndent": "{paragraphIndent.0}",
          "textCase": "{textCase.none}",
          "textDecoration": "{textDecoration.none}"
        },
        "type": "typography"
      },
      "XS": {
        "value": {
          "fontFamily": "{Pretendard}",
          "fontWeight": "{medium}",
          "lineHeight": "{1Row.lineHeight-100}",
          "fontSize": "{text-100}",
          "letterSpacing": "{letterSpacing.0}",
          "paragraphSpacing": "{paragraphSpacing.0}",
          "paragraphIndent": "{paragraphIndent.0}",
          "textCase": "{textCase.none}",
          "textDecoration": "{textDecoration.none}"
        },
        "type": "typography"
      }
    },
    "Detail": {
      "XL": {
        "value": {
          "fontFamily": "{Pretendard}",
          "fontWeight": "{regular}",
          "lineHeight": "{1Row.lineHeight-200}",
          "fontSize": "{text-200}",
          "letterSpacing": "{letterSpacing.0}",
          "paragraphSpacing": "{paragraphSpacing.0}",
          "paragraphIndent": "{paragraphIndent.0}",
          "textCase": "{textCase.none}",
          "textDecoration": "{textDecoration.none}"
        },
        "type": "typography"
      },
      "L": {
        "value": {
          "fontFamily": "{Pretendard}",
          "fontWeight": "{regular}",
          "lineHeight": "{1Row.lineHeight-100}",
          "fontSize": "{text-100}",
          "letterSpacing": "{letterSpacing.0}",
          "paragraphSpacing": "{paragraphSpacing.0}",
          "paragraphIndent": "{paragraphIndent.0}",
          "textCase": "{textCase.none}",
          "textDecoration": "{textDecoration.none}"
        },
        "type": "typography"
      },
      "M": {
        "value": {
          "fontFamily": "{Pretendard}",
          "fontWeight": "{medium}",
          "lineHeight": "{1Row.lineHeight-75}",
          "fontSize": "{text-75}",
          "letterSpacing": "{letterSpacing.0}",
          "paragraphSpacing": "{paragraphSpacing.0}",
          "paragraphIndent": "{paragraphIndent.0}",
          "textCase": "{textCase.none}",
          "textDecoration": "{textDecoration.none}"
        },
        "type": "typography"
      },
      "S": {
        "value": {
          "fontFamily": "{Pretendard}",
          "fontWeight": "{medium}",
          "lineHeight": "{1Row.lineHeight-50}",
          "fontSize": "{text-50}",
          "letterSpacing": "{letterSpacing.0}",
          "paragraphSpacing": "{paragraphSpacing.0}",
          "paragraphIndent": "{paragraphIndent.0}",
          "textCase": "{textCase.none}",
          "textDecoration": "{textDecoration.none}"
        },
        "type": "typography"
      }
    },
    "shadow00": {
      "value": [
        {
          "x": "0",
          "y": "0",
          "blur": "4",
          "spread": "0",
          "color": "#6D758305",
          "type": "dropShadow"
        },
        {
          "x": "0",
          "y": "0",
          "blur": "16",
          "spread": "0",
          "color": "#6D758305",
          "type": "dropShadow"
        }
      ],
      "type": "boxShadow"
    },
    "shadow04": {
      "value": [
        {
          "x": "0",
          "y": "4",
          "blur": "12",
          "spread": "0",
          "color": "#6D75830A",
          "type": "dropShadow"
        },
        {
          "x": "0",
          "y": "-4",
          "blur": "24",
          "spread": "0",
          "color": "#6D75830A",
          "type": "dropShadow"
        }
      ],
      "type": "boxShadow"
    },
    "shadow08": {
      "value": [
        {
          "x": "0",
          "y": "8",
          "blur": "16",
          "spread": "0",
          "color": "#6D758314",
          "type": "dropShadow"
        },
        {
          "x": "0",
          "y": "-8",
          "blur": "32",
          "spread": "0",
          "color": "#6D758314",
          "type": "dropShadow"
        }
      ],
      "type": "boxShadow"
    },
    "shadow16": {
      "value": [
        {
          "x": "0",
          "y": "16",
          "blur": "24",
          "spread": "0",
          "color": "#6D75831F",
          "type": "dropShadow"
        },
        {
          "x": "0",
          "y": "-12",
          "blur": "40",
          "spread": "0",
          "color": "#6D75831A",
          "type": "dropShadow"
        }
      ],
      "type": "boxShadow"
    },
    "shadow24": {
      "value": [
        {
          "x": "0",
          "y": "24",
          "blur": "32",
          "spread": "0",
          "color": "#6D758329",
          "type": "dropShadow"
        },
        {
          "x": "0",
          "y": "-16",
          "blur": "48",
          "spread": "0",
          "color": "#6D75831F",
          "type": "dropShadow"
        }
      ],
      "type": "boxShadow"
    },
    "shadow32": {
      "value": [
        {
          "x": "0",
          "y": "32",
          "blur": "40",
          "spread": "0",
          "color": "#6D758333",
          "type": "dropShadow"
        },
        {
          "x": "0",
          "y": "-24",
          "blur": "56",
          "spread": "0",
          "color": "#6D75831F",
          "type": "dropShadow"
        }
      ],
      "type": "boxShadow"
    },
    "shadow36": {
      "value": [
        {
          "x": "0",
          "y": "36",
          "blur": "48",
          "spread": "0",
          "color": "#6D75833D",
          "type": "dropShadow"
        },
        {
          "x": "0",
          "y": "-32",
          "blur": "64",
          "spread": "0",
          "color": "#6D75831F",
          "type": "dropShadow"
        }
      ],
      "type": "boxShadow"
    },
    "BlingGray": {
      "blingGray-25": {
        "value": "#FBFCFD",
        "type": "color"
      },
      "blingGray-50": {
        "value": "#F8F9FA",
        "type": "color"
      },
      "blingGray-75": {
        "value": "#F1F3F5",
        "type": "color"
      },
      "blingGray-100": {
        "value": "#ECEEF0",
        "type": "color"
      },
      "blingGray-200": {
        "value": "#DFE3E6",
        "type": "color"
      },
      "blingGray-300": {
        "value": "#D7DBDF",
        "type": "color"
      },
      "blingGray-400": {
        "value": "#B7BEC8",
        "type": "color"
      },
      "blingGray-500": {
        "value": "#969FAC",
        "type": "color"
      },
      "blingGray-600": {
        "value": "#6D7583",
        "type": "color"
      },
      "blingGray-700": {
        "value": "#525965",
        "type": "color"
      },
      "blingGray-800": {
        "value": "#2E3137",
        "type": "color"
      },
      "blingGray-900": {
        "value": "#11181C",
        "type": "color"
      }
    },
    "BlackA": {
      "blackA-25": {
        "value": "#00000003",
        "type": "color"
      },
      "blackA-50": {
        "value": "#00000008",
        "type": "color"
      },
      "blackA-75": {
        "value": "#0000000D",
        "type": "color"
      },
      "blackA-100": {
        "value": "#00000012",
        "type": "color"
      },
      "blackA-200": {
        "value": "#00000017",
        "type": "color"
      },
      "blackA-300": {
        "value": "#0000001C",
        "type": "color"
      },
      "blackA-400": {
        "value": "#00000024",
        "type": "color"
      },
      "blackA-500": {
        "value": "#00000038",
        "type": "color"
      },
      "blackA-600": {
        "value": "#00000070",
        "type": "color"
      },
      "blackA-700": {
        "value": "#0000007A",
        "type": "color"
      },
      "blackA-800": {
        "value": "#0000008F",
        "type": "color"
      },
      "blackA-900": {
        "value": "#000000E6",
        "type": "color"
      }
    },
    "WhiteA": {
      "whiteA-25": {
        "value": "#FFFFFF00",
        "type": "color"
      },
      "whiteA-50": {
        "value": "#FFFFFF03",
        "type": "color"
      },
      "whiteA-75": {
        "value": "#FFFFFF0A",
        "type": "color"
      },
      "whiteA-100": {
        "value": "#FFFFFF0F",
        "type": "color"
      },
      "whiteA-200": {
        "value": "#FFFFFF17",
        "type": "color"
      },
      "whiteA-300": {
        "value": "#FFFFFF21",
        "type": "color"
      },
      "whiteA-400": {
        "value": "#FFFFFF2E",
        "type": "color"
      },
      "whiteA-500": {
        "value": "#FFFFFF40",
        "type": "color"
      },
      "whiteA-600": {
        "value": "#FFFFFF61",
        "type": "color"
      },
      "whiteA-700": {
        "value": "#FFFFFF73",
        "type": "color"
      },
      "whiteA-800": {
        "value": "#FFFFFF96",
        "type": "color"
      },
      "whiteA-900": {
        "value": "#FFFFFFEB",
        "type": "color"
      }
    },
    "borderRadius-None": {
      "value": "0",
      "type": "borderRadius"
    },
    "borderRadius-XXSmall": {
      "value": "2",
      "type": "borderRadius"
    },
    "borderRadius-XSmall": {
      "value": "4",
      "type": "borderRadius"
    },
    "borderRadius-Small": {
      "value": "8",
      "type": "borderRadius"
    },
    "borderRadius-Medium(Base)": {
      "value": "10",
      "type": "borderRadius"
    },
    "borderRadius-Large": {
      "value": "12",
      "type": "borderRadius"
    },
    "borderRadius-XLarge": {
      "value": "16",
      "type": "borderRadius"
    },
    "borderRadius-XXLarge": {
      "value": "24",
      "type": "borderRadius"
    },
    "borderRadius-Circle": {
      "value": "100",
      "type": "borderRadius"
    },
    "stroke-50": {
      "value": "0.6",
      "type": "borderWidth"
    },
    "stroke-100": {
      "value": "1",
      "type": "borderWidth"
    },
    "stroke-200": {
      "value": "1.4",
      "type": "borderWidth"
    },
    "stroke-300": {
      "value": "2",
      "type": "borderWidth"
    },
    "stroke-400": {
      "value": "3",
      "type": "borderWidth"
    },
    "stroke-500": {
      "value": "4",
      "type": "borderWidth"
    },
    "BlingPrimary": {
      "blingPrimary-25": {
        "value": "#FFFCFB",
        "type": "color"
      },
      "blingPrimary-50": {
        "value": "#FEF7F5",
        "type": "color"
      },
      "blingPrimary-75": {
        "value": "#FEEFEB",
        "type": "color"
      },
      "blingPrimary-100": {
        "value": "#FAE1DA",
        "type": "color"
      },
      "blingPrimary-200": {
        "value": "#FAD5CC",
        "type": "color"
      },
      "blingPrimary-300": {
        "value": "#F9BBAC",
        "type": "color"
      },
      "blingPrimary-400": {
        "value": "#FC9E87",
        "type": "color"
      },
      "blingPrimary-500": {
        "value": "#FD7B5B",
        "type": "color"
      },
      "blingPrimary-600": {
        "value": "#F94114",
        "type": "color"
      },
      "blingPrimary-700": {
        "value": "#DF350B",
        "type": "color"
      },
      "blingPrimary-800": {
        "value": "#C72C06",
        "type": "color"
      },
      "blingPrimary-900": {
        "value": "#4D1B0F",
        "type": "color"
      }
    },
    "PrimaryColors": {
      "primaryMain": {
        "value": "#F94114",
        "type": "color"
      },
      "\bprimarySub": {
        "value": "#FC5C17",
        "type": "color"
      }
    },
    "SecondaryColors": {
      "SecondaryInfo": {
        "secondaryBlue-50": {
          "value": "#EFF6FF",
          "type": "color"
        },
        "secondaryBlue-100": {
          "value": "#C0D9F8",
          "type": "color"
        },
        "secondaryBlue-300": {
          "value": "#79B0F7",
          "type": "color"
        },
        "secondaryBlue-500": {
          "value": "#0D74F6",
          "type": "color"
        },
        "secondaryBlue-700": {
          "value": "#234EC6",
          "type": "color"
        }
      },
      "SecondarySubInfo": {
        "secondaryNavi-100": {
          "value": "#C9D0E1",
          "type": "color"
        },
        "secondaryNavi-300": {
          "value": "#97A2BB",
          "type": "color"
        },
        "secondaryNavi-400": {
          "value": "#717B98",
          "type": "color"
        },
        "secondaryNavi-500": {
          "value": "#505C81",
          "type": "color"
        },
        "secondaryNavi-600": {
          "value": "#324066",
          "type": "color"
        },
        "secondaryNavi-700": {
          "value": "#242F53",
          "type": "color"
        },
        "secondaryNavi-800": {
          "value": "#18223A",
          "type": "color"
        }
      },
      "SecondaryPositive": {
        "secondaryGreen-200": {
          "value": "#EAF8F2",
          "type": "color"
        },
        "secondaryGreen-400": {
          "value": "#22C983",
          "type": "color"
        },
        "secondaryGreen-600": {
          "value": "#0AAA66",
          "type": "color"
        }
      },
      "SecondaryNegative": {
        "secondaryRed-200": {
          "value": "#FFF3F3",
          "type": "color"
        },
        "secondaryRed-400": {
          "value": "#F96267",
          "type": "color"
        },
        "secondaryRed-600": {
          "value": "#E54147",
          "type": "color"
        }
      },
      "SecondaryCaution": {
        "secondaryYellow-200": {
          "value": "#FFF8E2",
          "type": "color"
        },
        "secondaryYellow-400": {
          "value": "#EFB603",
          "type": "color"
        },
        "secondaryYellow-600": {
          "value": "#E17A01",
          "type": "color"
        }
      }
    },
    "BrandColors": {
      "BlingOranage": {
        "blingOrange-25": {
          "value": "#FEFCFB",
          "type": "color"
        },
        "blingOrange-50": {
          "value": "#FEF8F4",
          "type": "color"
        },
        "blingOrange-75": {
          "value": "#FFF1E7",
          "type": "color"
        },
        "blingOrange-100": {
          "value": "#FFE8D7",
          "type": "color"
        },
        "blingOrange-200": {
          "value": "#FFDCC3",
          "type": "color"
        },
        "blingOrange-300": {
          "value": "#FFCCA7",
          "type": "color"
        },
        "blingOrange-400": {
          "value": "#FFB381",
          "type": "color"
        },
        "blingOrange-500": {
          "value": "#FA934E",
          "type": "color"
        },
        "blingOrange-600": {
          "value": "#F76808",
          "type": "color"
        },
        "blingOrange-700": {
          "value": "#ED5F00",
          "type": "color"
        },
        "blingOrange-800": {
          "value": "#BD4B00",
          "type": "color"
        },
        "blingOrange-900": {
          "value": "#451E11",
          "type": "color"
        }
      },
      "BlingPimento": {
        "blingPimento-25": {
          "value": "#FFFCFC",
          "type": "color"
        },
        "blingPimento-50": {
          "value": "#FFF8F7",
          "type": "color"
        },
        "blingPimento-75": {
          "value": "#FFF0EE",
          "type": "color"
        },
        "blingPimento-100": {
          "value": "#FFE6E2",
          "type": "color"
        },
        "blingPimento-200": {
          "value": "#FDD8D3",
          "type": "color"
        },
        "blingPimento-300": {
          "value": "#FAC7BE",
          "type": "color"
        },
        "blingPimento-400": {
          "value": "#F3B0A2",
          "type": "color"
        },
        "blingPimento-500": {
          "value": "#EA9280",
          "type": "color"
        },
        "blingPimento-600": {
          "value": "#E54D2E",
          "type": "color"
        },
        "blingPimento-700": {
          "value": "#DB4324",
          "type": "color"
        },
        "blingPimento-800": {
          "value": "#CA3214",
          "type": "color"
        },
        "blingPimento-900": {
          "value": "#341711",
          "type": "color"
        }
      },
      "BlingRed": {
        "blingRed-25": {
          "value": "#FFFCFC",
          "type": "color"
        },
        "blingRed-50": {
          "value": "#FFF8F8",
          "type": "color"
        },
        "blingRed-75": {
          "value": "#FFEFEF",
          "type": "color"
        },
        "blingRed-100": {
          "value": "#FFE5E5",
          "type": "color"
        },
        "blingRed-200": {
          "value": "#FDD8D8",
          "type": "color"
        },
        "blingRed-300": {
          "value": "#F9C6C6",
          "type": "color"
        },
        "blingRed-400": {
          "value": "#F3AEAF",
          "type": "color"
        },
        "blingRed-500": {
          "value": "#EB9091",
          "type": "color"
        },
        "blingRed-600": {
          "value": "#E5484D",
          "type": "color"
        },
        "blingRed-700": {
          "value": "#DC3D43",
          "type": "color"
        },
        "blingRed-800": {
          "value": "#CD2B31",
          "type": "color"
        },
        "blingRed-900": {
          "value": "#381316",
          "type": "color"
        }
      },
      "BlingCrimson": {
        "blingCrimson-25": {
          "value": "#FFFCFD",
          "type": "color"
        },
        "blingCrimson-50": {
          "value": "#FFF7FB",
          "type": "color"
        },
        "blingCrimson-75": {
          "value": "#FEEFF6",
          "type": "color"
        },
        "blingCrimson-100": {
          "value": "#FCE5F0",
          "type": "color"
        },
        "blingCrimson-200": {
          "value": "#F9D8E7",
          "type": "color"
        },
        "blingCrimson-300": {
          "value": "#F4C6DB",
          "type": "color"
        },
        "blingCrimson-400": {
          "value": "#EDADC8",
          "type": "color"
        },
        "blingCrimson-500": {
          "value": "#E58FB1",
          "type": "color"
        },
        "blingCrimson-600": {
          "value": "#E93D82",
          "type": "color"
        },
        "blingCrimson-700": {
          "value": "#E03177",
          "type": "color"
        },
        "blingCrimson-800": {
          "value": "#D31E66",
          "type": "color"
        },
        "blingCrimson-900": {
          "value": "#3D0D1D",
          "type": "color"
        }
      },
      "BlingPink": {
        "blingPink-25": {
          "value": "#FFFCFE",
          "type": "color"
        },
        "blingPink-50": {
          "value": "#FFF7FC",
          "type": "color"
        },
        "blingPink-75": {
          "value": "#FEEEF8",
          "type": "color"
        },
        "blingPink-100": {
          "value": "#FCE5F3",
          "type": "color"
        },
        "blingPink-200": {
          "value": "#F9D8EC",
          "type": "color"
        },
        "blingPink-300": {
          "value": "#F3C6E2",
          "type": "color"
        },
        "blingPink-400": {
          "value": "#ECADD4",
          "type": "color"
        },
        "blingPink-500": {
          "value": "#E38EC3",
          "type": "color"
        },
        "blingPink-600": {
          "value": "#D6409F",
          "type": "color"
        },
        "blingPink-700": {
          "value": "#D23197",
          "type": "color"
        },
        "blingPink-800": {
          "value": "#CD1D8D",
          "type": "color"
        },
        "blingPink-900": {
          "value": "#3B0A2A",
          "type": "color"
        }
      },
      "BlingPlum": {
        "blingPlum-25": {
          "value": "#FEFCFF",
          "type": "color"
        },
        "blingPlum-50": {
          "value": "#FFF8FF",
          "type": "color"
        },
        "blingPlum-75": {
          "value": "#FCEFFC",
          "type": "color"
        },
        "blingPlum-100": {
          "value": "#F9E5F9",
          "type": "color"
        },
        "blingPlum-200": {
          "value": "#F3D9F4",
          "type": "color"
        },
        "blingPlum-300": {
          "value": "#EBC8ED",
          "type": "color"
        },
        "blingPlum-400": {
          "value": "#DFAFE3",
          "type": "color"
        },
        "blingPlum-500": {
          "value": "#CF91D8",
          "type": "color"
        },
        "blingPlum-600": {
          "value": "#AB4ABA",
          "type": "color"
        },
        "blingPlum-700": {
          "value": "#A43CB4",
          "type": "color"
        },
        "blingPlum-800": {
          "value": "#9C2BAD",
          "type": "color"
        },
        "blingPlum-900": {
          "value": "#340C3B",
          "type": "color"
        }
      },
      "BlingPurple": {
        "blingPurple-25": {
          "value": "#FEFCFE",
          "type": "color"
        },
        "blingPurple-50": {
          "value": "#FDFAFF",
          "type": "color"
        },
        "blingPurple-75": {
          "value": "#F9F1FE",
          "type": "color"
        },
        "blingPurple-100": {
          "value": "#F3E7FC",
          "type": "color"
        },
        "blingPurple-200": {
          "value": "#EDDBF9",
          "type": "color"
        },
        "blingPurple-300": {
          "value": "#E3CCF4",
          "type": "color"
        },
        "blingPurple-400": {
          "value": "#D3B4ED",
          "type": "color"
        },
        "blingPurple-500": {
          "value": "#BE93E4",
          "type": "color"
        },
        "blingPurple-600": {
          "value": "#8E4EC6",
          "type": "color"
        },
        "blingPurple-700": {
          "value": "#8445BC",
          "type": "color"
        },
        "blingPurple-800": {
          "value": "#793AAF",
          "type": "color"
        },
        "blingPurple-900": {
          "value": "#2B0E44",
          "type": "color"
        }
      },
      "BlingViolet": {
        "blingViolet-25": {
          "value": "#FDFCFE",
          "type": "color"
        },
        "blingViolet-50": {
          "value": "#FBFAFF",
          "type": "color"
        },
        "blingViolet-75": {
          "value": "#F5F2FF",
          "type": "color"
        },
        "blingViolet-100": {
          "value": "#EDE9FE",
          "type": "color"
        },
        "blingViolet-200": {
          "value": "#E4DEFC",
          "type": "color"
        },
        "blingViolet-300": {
          "value": "#D7CFF9",
          "type": "color"
        },
        "blingViolet-400": {
          "value": "#C4B8F3",
          "type": "color"
        },
        "blingViolet-500": {
          "value": "#AA99EC",
          "type": "color"
        },
        "blingViolet-600": {
          "value": "#6E56CF",
          "type": "color"
        },
        "blingViolet-700": {
          "value": "#644FC1",
          "type": "color"
        },
        "blingViolet-800": {
          "value": "#5746AF",
          "type": "color"
        },
        "blingViolet-900": {
          "value": "#20134B",
          "type": "color"
        }
      },
      "BlingIndigo": {
        "blingIndigo-25": {
          "value": "#FDFDFE",
          "type": "color"
        },
        "blingIndigo-50": {
          "value": "#F8FAFF",
          "type": "color"
        },
        "blingIndigo-75": {
          "value": "#F0F4FF",
          "type": "color"
        },
        "blingIndigo-100": {
          "value": "#E6EDFE",
          "type": "color"
        },
        "blingIndigo-200": {
          "value": "#D9E2FC",
          "type": "color"
        },
        "blingIndigo-300": {
          "value": "#C6D4F9",
          "type": "color"
        },
        "blingIndigo-400": {
          "value": "#AEC0F5",
          "type": "color"
        },
        "blingIndigo-500": {
          "value": "#8DA4EF",
          "type": "color"
        },
        "blingIndigo-600": {
          "value": "#3E63DD",
          "type": "color"
        },
        "blingIndigo-700": {
          "value": "#3A5CCC",
          "type": "color"
        },
        "blingIndigo-800": {
          "value": "#3451B2",
          "type": "color"
        },
        "blingIndigo-900": {
          "value": "#101D46",
          "type": "color"
        }
      },
      "BlingBlue": {
        "blingBlue-25": {
          "value": "#FBFDFF",
          "type": "color"
        },
        "blingBlue-50": {
          "value": "#F5FAFF",
          "type": "color"
        },
        "blingBlue-75": {
          "value": "#EDF6FF",
          "type": "color"
        },
        "blingBlue-100": {
          "value": "#E1F0FF",
          "type": "color"
        },
        "blingBlue-200": {
          "value": "#CEE7FE",
          "type": "color"
        },
        "blingBlue-300": {
          "value": "#B7D9F8",
          "type": "color"
        },
        "blingBlue-400": {
          "value": "#96C7F2",
          "type": "color"
        },
        "blingBlue-500": {
          "value": "#5EB0EF",
          "type": "color"
        },
        "blingBlue-600": {
          "value": "#0091FF",
          "type": "color"
        },
        "blingBlue-700": {
          "value": "#0081F1",
          "type": "color"
        },
        "blingBlue-800": {
          "value": "#006ADC",
          "type": "color"
        },
        "blingBlue-900": {
          "value": "#00254D",
          "type": "color"
        }
      },
      "BlingCyan": {
        "blingCyan-25": {
          "value": "#FAFDFE",
          "type": "color"
        },
        "blingCyan-50": {
          "value": "#F2FCFD",
          "type": "color"
        },
        "blingCyan-75": {
          "value": "#E7F9FB",
          "type": "color"
        },
        "blingCyan-100": {
          "value": "#D8F3F6",
          "type": "color"
        },
        "blingCyan-200": {
          "value": "#C4EAEF",
          "type": "color"
        },
        "blingCyan-300": {
          "value": "#AADEE6",
          "type": "color"
        },
        "blingCyan-400": {
          "value": "#84CDDA",
          "type": "color"
        },
        "blingCyan-500": {
          "value": "#3DB9CF",
          "type": "color"
        },
        "blingCyan-600": {
          "value": "#05A2C2",
          "type": "color"
        },
        "blingCyan-700": {
          "value": "#0894B3",
          "type": "color"
        },
        "blingCyan-800": {
          "value": "#0C7792",
          "type": "color"
        },
        "blingCyan-900": {
          "value": "#04313C",
          "type": "color"
        }
      },
      "BlingTeal": {
        "blingTeal-25": {
          "value": "#FAFEFD",
          "type": "color"
        },
        "blingTeal-50": {
          "value": "#F1FCFA",
          "type": "color"
        },
        "blingTeal-75": {
          "value": "#E7F9F5",
          "type": "color"
        },
        "blingTeal-100": {
          "value": "#D9F3EE",
          "type": "color"
        },
        "blingTeal-200": {
          "value": "#C7EBE5",
          "type": "color"
        },
        "blingTeal-300": {
          "value": "#AFDFD7",
          "type": "color"
        },
        "blingTeal-400": {
          "value": "#8DCEC3",
          "type": "color"
        },
        "blingTeal-500": {
          "value": "#53B9AB",
          "type": "color"
        },
        "blingTeal-600": {
          "value": "#12A594",
          "type": "color"
        },
        "blingTeal-700": {
          "value": "#0E9888",
          "type": "color"
        },
        "blingTeal-800": {
          "value": "#067A6F",
          "type": "color"
        },
        "blingTeal-900": {
          "value": "#10302B",
          "type": "color"
        }
      },
      "BlingGreen": {
        "blingGreen-25": {
          "value": "#FBFEFC",
          "type": "color"
        },
        "blingGreen-50": {
          "value": "#F2FCF5",
          "type": "color"
        },
        "blingGreen-75": {
          "value": "#E9F9EE",
          "type": "color"
        },
        "blingGreen-100": {
          "value": "#DDF3E4",
          "type": "color"
        },
        "blingGreen-200": {
          "value": "#CCEBD7",
          "type": "color"
        },
        "blingGreen-300": {
          "value": "#B4DFC4",
          "type": "color"
        },
        "blingGreen-400": {
          "value": "#92CEAC",
          "type": "color"
        },
        "blingGreen-500": {
          "value": "#5BB98C",
          "type": "color"
        },
        "blingGreen-600": {
          "value": "#30A46C",
          "type": "color"
        },
        "blingGreen-700": {
          "value": "#299764",
          "type": "color"
        },
        "blingGreen-800": {
          "value": "#18794E",
          "type": "color"
        },
        "blingGreen-900": {
          "value": "#153226",
          "type": "color"
        }
      },
      "BlingGrass": {
        "blingGrass-25": {
          "value": "#FBFEFB",
          "type": "color"
        },
        "blingGrass-50": {
          "value": "#F3FCF3",
          "type": "color"
        },
        "blingGrass-75": {
          "value": "#EBF9EB",
          "type": "color"
        },
        "blingGrass-100": {
          "value": "#DFF3DF",
          "type": "color"
        },
        "blingGrass-200": {
          "value": "#CEEBCF",
          "type": "color"
        },
        "blingGrass-300": {
          "value": "#B7DFBA",
          "type": "color"
        },
        "blingGrass-400": {
          "value": "#97CF9C",
          "type": "color"
        },
        "blingGrass-500": {
          "value": "#65BA75",
          "type": "color"
        },
        "blingGrass-600": {
          "value": "#46A758",
          "type": "color"
        },
        "blingGrass-700": {
          "value": "#3D9A50",
          "type": "color"
        },
        "blingGrass-800": {
          "value": "#297C3B",
          "type": "color"
        },
        "blingGrass-900": {
          "value": "#1B311E",
          "type": "color"
        }
      },
      "BlingBrown": {
        "blingBrown-25": {
          "value": "#FEFDFC",
          "type": "color"
        },
        "blingBrown-50": {
          "value": "#FCF9F6",
          "type": "color"
        },
        "blingBrown-75": {
          "value": "#F8F1EA",
          "type": "color"
        },
        "blingBrown-100": {
          "value": "#F4E9DD",
          "type": "color"
        },
        "blingBrown-200": {
          "value": "#EFDDCC",
          "type": "color"
        },
        "blingBrown-300": {
          "value": "#E8CDB5",
          "type": "color"
        },
        "blingBrown-400": {
          "value": "#DDB896",
          "type": "color"
        },
        "blingBrown-500": {
          "value": "#D09E72",
          "type": "color"
        },
        "blingBrown-600": {
          "value": "#AD7F58",
          "type": "color"
        },
        "blingBrown-700": {
          "value": "#A07653",
          "type": "color"
        },
        "blingBrown-800": {
          "value": "#886349",
          "type": "color"
        },
        "blingBrown-900": {
          "value": "#3F2C22",
          "type": "color"
        }
      },
      "BlingBronze": {
        "blingBronze-25": {
          "value": "#FDFCFC",
          "type": "color"
        },
        "blingBronze-50": {
          "value": "#FDF8F6",
          "type": "color"
        },
        "blingBronze-75": {
          "value": "#F8F1EE",
          "type": "color"
        },
        "blingBronze-100": {
          "value": "#F2E8E4",
          "type": "color"
        },
        "blingBronze-200": {
          "value": "#EADDD7",
          "type": "color"
        },
        "blingBronze-300": {
          "value": "#E0CEC7",
          "type": "color"
        },
        "blingBronze-400": {
          "value": "#D1B9B0",
          "type": "color"
        },
        "blingBronze-500": {
          "value": "#BFA094",
          "type": "color"
        },
        "blingBronze-600": {
          "value": "#A18072",
          "type": "color"
        },
        "blingBronze-700": {
          "value": "#977669",
          "type": "color"
        },
        "blingBronze-800": {
          "value": "#846358",
          "type": "color"
        },
        "blingBronze-900": {
          "value": "#43302B",
          "type": "color"
        }
      },
      "BlingGold": {
        "blingGold-25": {
          "value": "#FDFDFC",
          "type": "color"
        },
        "blingGold-50": {
          "value": "#FBF9F2",
          "type": "color"
        },
        "blingGold-75": {
          "value": "#F5F2E9",
          "type": "color"
        },
        "blingGold-100": {
          "value": "#EEEADD",
          "type": "color"
        },
        "blingGold-200": {
          "value": "#E5DFD0",
          "type": "color"
        },
        "blingGold-300": {
          "value": "#DAD1BD",
          "type": "color"
        },
        "blingGold-400": {
          "value": "#CBBDA4",
          "type": "color"
        },
        "blingGold-500": {
          "value": "#B8A383",
          "type": "color"
        },
        "blingGold-600": {
          "value": "#978365",
          "type": "color"
        },
        "blingGold-700": {
          "value": "#8C795D",
          "type": "color"
        },
        "blingGold-800": {
          "value": "#776750",
          "type": "color"
        },
        "blingGold-900": {
          "value": "#3B352B",
          "type": "color"
        }
      },
      "BlingSky": {
        "blingSky-25": {
          "value": "#F9FEFF",
          "type": "color"
        },
        "blingSky-50": {
          "value": "#F1FCFF",
          "type": "color"
        },
        "blingSky-75": {
          "value": "#E4F9FF",
          "type": "color"
        },
        "blingSky-100": {
          "value": "#D5F4FD",
          "type": "color"
        },
        "blingSky-200": {
          "value": "#C1ECF9",
          "type": "color"
        },
        "blingSky-300": {
          "value": "#A4DFF1",
          "type": "color"
        },
        "blingSky-400": {
          "value": "#79CFEA",
          "type": "color"
        },
        "blingSky-500": {
          "value": "#2EBDE5",
          "type": "color"
        },
        "blingSky-600": {
          "value": "#68DDFD",
          "type": "color"
        },
        "blingSky-700": {
          "value": "#5FD4F4",
          "type": "color"
        },
        "blingSky-800": {
          "value": "#0078A1",
          "type": "color"
        },
        "blingSky-900": {
          "value": "#003242",
          "type": "color"
        }
      },
      "BlingMint": {
        "blingMint-25": {
          "value": "#F9FEFD",
          "type": "color"
        },
        "blingMint-50": {
          "value": "#EFFEFA",
          "type": "color"
        },
        "blingMint-75": {
          "value": "#E1FBF4",
          "type": "color"
        },
        "blingMint-100": {
          "value": "#D2F7ED",
          "type": "color"
        },
        "blingMint-200": {
          "value": "#C0EFE3",
          "type": "color"
        },
        "blingMint-300": {
          "value": "#A5E4D4",
          "type": "color"
        },
        "blingMint-400": {
          "value": "#7DD4C0",
          "type": "color"
        },
        "blingMint-500": {
          "value": "#40C4AA",
          "type": "color"
        },
        "blingMint-600": {
          "value": "#70E1C8",
          "type": "color"
        },
        "blingMint-700": {
          "value": "#69D9C1",
          "type": "color"
        },
        "blingMint-800": {
          "value": "#147D6F",
          "type": "color"
        },
        "blingMint-900": {
          "value": "#09342E",
          "type": "color"
        }
      },
      "BlingLime": {
        "blingLime-25": {
          "value": "#FCFDFA",
          "type": "color"
        },
        "blingLime-50": {
          "value": "#F7FCF0",
          "type": "color"
        },
        "blingLime-75": {
          "value": "#EEFADC",
          "type": "color"
        },
        "blingLime-100": {
          "value": "#E4F7C7",
          "type": "color"
        },
        "blingLime-200": {
          "value": "#D7F2B0",
          "type": "color"
        },
        "blingLime-300": {
          "value": "#C9E894",
          "type": "color"
        },
        "blingLime-400": {
          "value": "#B1D16A",
          "type": "color"
        },
        "blingLime-500": {
          "value": "#94BA2C",
          "type": "color"
        },
        "blingLime-600": {
          "value": "#99D52A",
          "type": "color"
        },
        "blingLime-700": {
          "value": "#93C926",
          "type": "color"
        },
        "blingLime-800": {
          "value": "#5D770D",
          "type": "color"
        },
        "blingLime-900": {
          "value": "#263209",
          "type": "color"
        }
      },
      "BlingYellow": {
        "blingYellow-25": {
          "value": "#FDFDF9",
          "type": "color"
        },
        "blingYellow-50": {
          "value": "#FFFCE8",
          "type": "color"
        },
        "blingYellow-75": {
          "value": "#FFFBD1",
          "type": "color"
        },
        "blingYellow-100": {
          "value": "#FFF8BB",
          "type": "color"
        },
        "blingYellow-200": {
          "value": "#FEF2A4",
          "type": "color"
        },
        "blingYellow-300": {
          "value": "#F9E68C",
          "type": "color"
        },
        "blingLime-400": {
          "value": "#EFD36C",
          "type": "color"
        },
        "blingYellow-500": {
          "value": "#EBBC00",
          "type": "color"
        },
        "blingYellow-600": {
          "value": "#F5D90A",
          "type": "color"
        },
        "blingYellow-700": {
          "value": "#F7CE00",
          "type": "color"
        },
        "blingYellow-800": {
          "value": "#946800",
          "type": "color"
        },
        "blingYellow-900": {
          "value": "#35290F",
          "type": "color"
        }
      },
      "BlingAmber": {
        "blingAmber-25": {
          "value": "#FEFDFB",
          "type": "color"
        },
        "blingAmber-50": {
          "value": "#FFF9ED",
          "type": "color"
        },
        "blingAmber-75": {
          "value": "#FFF4D5",
          "type": "color"
        },
        "blingAmber-100": {
          "value": "#FFECBC",
          "type": "color"
        },
        "blingAmber-200": {
          "value": "#FFE3A2",
          "type": "color"
        },
        "blingAmber-300": {
          "value": "#FFD386",
          "type": "color"
        },
        "blingAmber-400": {
          "value": "#F3BA63",
          "type": "color"
        },
        "blingAmber-500": {
          "value": "#EE9D2B",
          "type": "color"
        },
        "blingAmber-600": {
          "value": "#FFB224",
          "type": "color"
        },
        "blingAmber-700": {
          "value": "#FFA01C",
          "type": "color"
        },
        "blingAmber-800": {
          "value": "#AD5700",
          "type": "color"
        },
        "blingAmber-900": {
          "value": "#4E2009",
          "type": "color"
        }
      }
    }
  },
  "$themes": [],
  "$metadata": {
    "tokenSetOrder": [
      "Core"
    ]
  }
}